pypaya/__init__.py
pypaya/example.py
strelitzia-0.0.1.dist-info/METADATA
strelitzia-0.0.1.dist-info/WHEEL
strelitzia-0.0.1.dist-info/licenses/LICENSE
strelitzia-0.0.1.dist-info/RECORD
