Metadata-Version: 2.1
Name: strelitzia
Version: 0.0.1
Summary: A python package for understanding the state of your requirements in table format
Project-URL: Homepage, https://github.com/sxgd/strelitzia
Project-URL: Bug Tracker, https://github.com/sxgd/strelitzia/issues
Author-email: Sash Nortier <author@example.com>
License: Copyright 2022 Sash Nortier
Classifier: License :: OSI Approved :: MIT License
Classifier: Operating System :: OS Independent
Classifier: Programming Language :: Python :: 3
Requires-Python: >=3.7
